{
  "version": 1,
  "basics": {
    "name": "Thomas Letsch Groch",
    "label": "Web Developer",
    "picture": "https://thomasgroch.xyz/avatar.png",
    "email": "thomas.groch@gmail.com",
    "phone": "‭",
    "website": "https://thomasgroch.xyz/",
    "summary": "Exercer atividades de desenvolvedor sênior de qualidade:\n• Monitoramento de infraestrutura e saúde da plataformas SaaS;\n• Análise e geração indicadores operacionais e de negócio;\n• Integrações entre sistemas (sincronização, agendamento e fila de processos);\nNo mais serei muito minucioso para que ambos tenhamos uma excelente experiência.",
    "highlights": null,
    "location": {
      "address": "",
      "postalCode": "",
      "city": "Florianópolis",
      "countryCode": "BR",
      "region": "SC"
    },
    "profiles": [
      {
        "network": "Linkedin",
        "username": "thomasgroch",
        "url": "https://www.linkedin.com/in/thomasgroch"
      },
      {
        "network": "Skype",
        "username": "thomas.groch",
        "url": "skype:thomasgroch?chat"
      }
    ]
  },
  "work": [
        {
      "type": 3,
      "company": "Workana widget",
      "position": "Desenvolvedor full stack",
      "website": "https://github.com/thomasgroch/workana-widget",
      "startDate": "2018",
      "summary": "O workana-widget é um widget que permite aos usuários do Workana monitorar os trabalhos mais recentes.",
      "highlights": [],
      "img": "https://user-images.githubusercontent.com/67318/68424371-970fe900-0182-11ea-9624-736e455e33e3.gif",
      "endDate": ""
    },
     {
      "type": 3,
      "company": "Resource Generator",
      "position": "Desenvolvedor full stack",
      "website": "https://github.com/thomasgroch/ResourceGenerator",
      "startDate": "2017",
      "summary": "Gere toda a estrutura para um determinado nome de recurso.",
      "highlights": [],
      "img": "avatar.png",
      "endDate": ""
    },
    {
      "type": 1,
      "company": "Hero99",
      "position": "Senior Web Application Developer",
      "website": "https://hero99.com.br/",
      "startDate": "2017",
      "summary": "Melhora da disponibilidade usando proxy reverso em docker integrado ao workflow de CI zero-downtime deployment. Solução de automação para agregar em tempo real mensageiros instantâneos  distintos (fb, whatsapp e instagram).",
      "highlights": [],
      "techs": [
        "avatar.png",
        "avatar.png"
      ],
      "img": "projects/hero99.png",
      "endDate": ""
    },
    {
      "type": 1,
      "company": "Langowski",
      "position": "Gerente de Projeto da Tecnologia da Informação",
      "website": "https://langowski.com.br/",
      "startDate": "2016",
      "summary": "Desenvolvimento de sistema de CRM Multitenancy. Implementação de gerenciador de empreendimentos, pessoas e empresas do projeto.",
      "highlights": [],
      "img": "projects/langowski.png",
      "endDate": ""
    },
    {
      "type": 1,
      "company": "TagBox",
      "position": "Analista de Sistemas Web",
      "website": "",
      "startDate": "2015",
      "summary": "Produção de Marketplace de moda com PHP, Codeigniter, RESTfull, Amazon AWS (EC2, AMIs, Elastic IPs, S3), Vagrant, Git-remote, cURL e XML Parser.",
      "highlights": [],
      "img": "projects/tagbox.png",
      "endDate": ""
    },
    {
      "type": 1,
      "company": "RESERVA",
      "position": "Analista de Sistemas",
      "website": "https://www.usereserva.com/",
      "startDate": "2014",
      "summary": "Desenvolvimento de API para integração do e-commerce da Reserva para portal de vendas MercadoLivre e ajudei a lidar com a grande escala de usuários.",
      "highlights": [],
      "img": "projects/reserva.png",
      "endDate": ""
    },
    {
      "type": 1,
      "company": "Artexpressa",
      "position": "Desenvolvedor full stack web",
      "website": "",
      "startDate": "2012",
      "summary": "Desenvolvimento de sistemas web em PHP/MYSQL. Modelagem de sistema gestão e agendamento de palestras. Implementação de funcionalidade para emissão de certificado digital.",
      "highlights": [],
      "img": "projects/artexpressa.png",
      "endDate": ""
    },
    {
      "type": 1,
      "company": "Arquitetura Abstrata",
      "position": "Desenvolvedor full stack web",
      "website": "https://arqabs.com/",
      "startDate": "2011",
      "summary": "Desenvolvimento de sistema de incubadoras de empresas. Implementação de gerenciador de empreendimentos, pessoas e empresas. Desenvolvimento de processo seletivo do empreendimento. Adaptação do módulo de gerenciamento financeiro empresarial.",
      "highlights": [],
      "img": "projects/arqabs.png",
      "endDate": ""
    },
    {
      "type": 1,
      "company": "Sephora Brasil",
      "position": "Desenvolvedor PHP / Analista de Dados",
      "website": "https://pesquisa.sephora.com.br/",
      "startDate": "2011",
      "summary": "Rotina de integração bidirecinal do gerenciamento de conteúdo com produtos.",
      "highlights": [],
      "img": "https://res.cloudinary.com/tgroch/image/upload/v1572470223/pesquisa-sephora-brasil_wte65i.png",
      "endDate": ""
    },
    {
      "type": 1,
      "company": "Forpix",
      "position": "Desenvolvedor / Analista de Dados",
      "website": "http://forpix.com.br/",
      "startDate": "2009",
      "summary": "Modelagem de sistema de CMS, levantamento de requisitos de acordo com necessidade apresentada pelo cliente. Prestação de serviços de desenvolvimento para experiência intuitiva.",
      "highlights": [],
      "img": "projects/forpix.png",
      "endDate": ""
    }
  ],
  "projects": [
    {
      "name": "Criação e Desenvolvimento PSC",
      "startDate": "2008-12-31",
      "summary": "Desenvolvimento de um CMS, programação de interface visual, diagramação e montagem do site PHP/MySql/HTML/CSS.",
      "url": "http://web.archive.org/web/20110817055820/http://site.psc.institucional.ws/",
      "endDate": ""
    }
  ],
  "additionalWork": [
    {
      "company": "",
      "position": "",
      "website": "",
      "startDate": "",
      "endDate": "",
      "summary": "",
      "highlights": [
        ""
      ]
    }
  ],
  "workLabel": "",
  "additionalWorkLabel": "",
  "education": [
    {
      "institution": "Instituto Tecnológico SENAC RJ",
      "area": "Graduação em Sistemas para Internet ",
      "studyType": "System Development",
      "startDate": "2008-12-31",
      "gpa": "",
      "courses": [],
      "endDate": "2011-12-31"
    },
    {
      "institution": "Instituto Tecnológico SENAC RJ",
      "area": "Tecnologia de Redes de Computadores ",
      "studyType": "Técnico",
      "startDate": "2005-02",
      "endDate": "2008-01",
      "gpa": "",
      "courses": [
        ""
      ]
    }
  ],
  "publications": [
    {
      "name": "",
      "publisher": "",
      "releaseDate": "",
      "website": "",
      "summary": "",
      "isbn": ""
    }
  ],
  "additionalPublications": [
    {
      "name": "",
      "publisher": "",
      "releaseDate": "",
      "website": "",
      "summary": "",
      "isbn": ""
    }
  ],
  "publicationsLabel": "",
  "additionalPublicationsLabel": "",
  "skills": [
    {
      "name": "PHP 7",
      "level": "Senior",
      "keywords": [
        "Laravel",
        "TDD",
        "Web Scraping"
      ]
    },
    {
      "name": "Comércio eletrônico",
      "level": "",
      "keywords": []
    },
    {
      "name": "RESTful API",
      "level": "Master",
      "keywords": []
    },
    {
      "name": "Amazon Web Services",
      "level": "",
      "keywords": []
    }
  ],
  "languages": [
    {
      "language": "Português",
      "fluency": "Natal"
    },
    {
      "language": "English",
      "fluency": "Fluent"
    }
  ],
  "stack": {
    "front": [
      {
        "name": "SASS",
        "photo": "stack/sass-logo.png",
        "href": "https://sass-lang.com"
      },
      {
        "name": "Stylus",
        "photo": "stack/stylus-logo.png",
        "href": "https://stylus-lang.com"
      },
      {
        "name": "jQuery",
        "photo": "stack/jquery-logo.png",
        "href": "https://jquery.com"
      },
      {
        "name": "TailwindCSS",
        "photo": "stack/tailwindcss-logo.png",
        "href": "https://tailwindcss.com"
      },
      {
        "name": "Vite",
        "photo": "stack/vite-logo.png",
        "href": "https://vuex.vuejs.org/"
      },
      {
        "name": "VueJS",
        "photo": "stack/vue-logo.png",
        "href": "https://vuejs.org"
      },
      {
        "name": "Axios",
        "photo": "stack/axios-logo.png",
        "href": "https://axios-http.com/docs/intro/"
      },
      {
        "name": "Vue Router",
        "photo": "stack/vue-logo.png",
        "href": "https://router.vuejs.org/"
      }
    ],
    "back": [
      {
        "name": "Laravel",
        "photo": "stack/laravel-logo.png",
        "href": "https://laravel.com"
      },
      {
        "name": "Node",
        "photo": "stack/node-logo.png",
        "href": "https://nodejs.org/"
      },
      {
        "name": "Nuxt",
        "photo": "stack/nuxt-logo.png",
        "href": "https://nuxtjs.org/"
      },
      {
        "name": "PHP",
        "photo": "stack/php-logo.png",
        "href": "https://php.net/"
      },
      {
        "name": "AdonisJS",
        "photo": "stack/adonis-logo.png",
        "href": "https://adonisjs.com"
      },
      {
        "name": "Bedrock",
        "photo": "stack/roots-logo.png",
        "href": "https://roots.io/bedrock/"
      },
      {
        "name": "RoR",
        "photo": "stack/ruby-logo.png",
        "href": "https://rubyonrails.org/"
      },
      {
        "name": "Lambda",
        "photo": "stack/lambda-logo.png",
        "href": "https://aws.amazon.com/lambda/"
      }
    ],
    "database": [
       {
        "name": "MariaDB",
        "photo": "stack/mariadb-logo.png",
        "href": "https://mariadb.com"
      },
       {
        "name": "MongoDB",
        "photo": "stack/mongo-logo.png",
        "href": "https://www.mongodb.org/"
      },
      {
        "name": "Redis",
        "photo": "stack/redis-logo.png",
        "href": "https://redis.io"
      },
      {
        "name": "GraphQL",
        "photo": "stack/graph-logo.png",
        "href": "https://graphql.org/"
      },
      {
        "name": "Postgres",
        "photo": "stack/postgres-logo.png",
        "href": "https://www.postgresql.org/"
      },
      {
        "name": "FaunaDB",
        "photo": "stack/fauna-logo.png",
        "href": "https://faunadb.com/"
      }   
    ],
    "infra": [
      {
        "name": "Docker",
        "photo": "stack/docker-logo.png",
        "href": "https://docker.com"
      },
      {
        "name": "Heroku",
        "photo": "stack/heroku-logo.png",
        "href": "https://heroku.com/"
      },
      {
        "name": "Netlify",
        "photo": "stack/netlify-logo.png",
        "href": "https://netlify.com/"
      },
      {
        "name": "AWS",
        "photo": "stack/aws-logo.png",
        "href": "https://aws.amazon.com/"
      }
    ],
    "misc": [
      {
        "name": "Git",
        "photo": "stack/git-logo.png",
        "href": "https://git-scm.com/"
      },
      {
        "name": "VisualParadigm",
        "photo": "stack/vp-logo.png",
        "href": "https:/www.visual-paradigm.com/"
      },
      {
        "name": "Nobackend",
        "photo": "stack/nobk-logo.png",
        "href": "http://nobackend.org/"
      },
      {
        "name": "Linux",
        "photo": "stack/linux-logo.png",
        "href": "https://www.linux.org/"
      },
      {
        "name": "MacOS",
        "photo": "stack/macos-logo.png",
        "href": "https://www.apple.com/macos/monterey/"
      },
      {
        "name": "Windows",
        "photo": "stack/windows-logo.png",
        "href": "https://www.microsoft.com/"
      },
      {
        "name": "WebStorm",
        "photo": "stack/webstorm-logo.png",
        "href": "https://www.jetbrains.com/webstorm/"
      },
      {
        "name": "Bash",
        "photo": "stack/bash-logo.png",
        "href": ""
      }
    ]
  }
}